{
  "enabled": true,
  "arrow": "→",
  "cards": [
    {
      "title": "Solar PV Panels",
      "description": "Generate your own clean electricity and reduce your bills by up to 70%",
      "href": "/solar-panels"
    },
    {
      "title": "Battery Storage",
      "description": "Store excess solar energy and use it when you need it most",
      "href": "/battery-storage"
    },
    {
      "title": "EV Chargers",
      "description": "Effortless, reliable charging for your electric vehicle at home",
      "href": "/ev-chargers"
    },
    {
      "title": "Commercial Solar",
      "description": "Cut operational costs with solar systems for businesses of any size",
      "href": "/commercial-solar"
    }
  ]
}
